py_yaml12-0.1.0.dist-info/METADATA
py_yaml12-0.1.0.dist-info/WHEEL
py_yaml12-0.1.0.dist-info/licenses/LICENSE
yaml12/__init__.py
yaml12/__init__.pyi
yaml12/py.typed
yaml12/yaml12.abi3.so
py_yaml12-0.1.0.dist-info/RECORD
