Metadata-Version: 2.4
Name: py-yaml12
Version: 0.1.0
Classifier: Development Status :: 4 - Beta
Classifier: Intended Audience :: Developers
Classifier: License :: OSI Approved :: MIT License
Classifier: Programming Language :: Python :: 3
Classifier: Programming Language :: Python :: 3 :: Only
Classifier: Programming Language :: Python :: 3.10
Classifier: Programming Language :: Python :: 3.11
Classifier: Programming Language :: Python :: 3.12
Classifier: Programming Language :: Python :: 3.13
Classifier: Programming Language :: Rust
Classifier: Programming Language :: Python :: Implementation :: CPython
Classifier: Programming Language :: Python :: Implementation :: PyPy
Classifier: Typing :: Typed
Classifier: Topic :: Software Development :: Libraries
Classifier: Topic :: Text Processing :: Markup
License-File: LICENSE
Summary: A modern YAML 1.2 parser and emitter for Python, written in Rust.
Keywords: yaml,parser,serializer,rust,pyo3,abi3
Author: Tomasz Kalinowski
Maintainer: Tomasz Kalinowski
Requires-Python: >=3.10
Project-URL: Homepage, https://github.com/posit-dev/py-yaml12
Project-URL: Documentation, https://posit-dev.github.io/py-yaml12/
Project-URL: Source, https://github.com/posit-dev/py-yaml12
Project-URL: Issues, https://github.com/posit-dev/py-yaml12/issues
